Metadata-Version: 1.1
Name: wpyfm
Version: 0.1.8
Summary: A pybind11 wrapper for libfm.
Home-page: UNKNOWN
Author: Karl Krauth
Author-email: karl.krauth@gmail.com
License: UNKNOWN
Download-URL: https://github.com/Karl-Krauth/libfm/archive/v0.1.8.tar.gz
Platform: UNKNOWN
